examples/__init__.py
examples/crawler_example.py
tor_expert/__init__.py
tor_expert/settings.py
tor_expert/tor.py
tor_expert-0.0.3.dist-info/METADATA
tor_expert-0.0.3.dist-info/WHEEL
tor_expert-0.0.3.dist-info/top_level.txt
tor_expert-0.0.3.dist-info/RECORD
