Metadata-Version: 2.1
Name: tor-expert
Version: 0.0.3
Summary: Using tor expert as service
Home-page: UNKNOWN
Author: Dragan Matesic
Author-email: dragan.matesic@gmail.com
License: MIT
Platform: UNKNOWN
Requires-Dist: requests
Requires-Dist: bs4
Requires-Dist: lxml
Requires-Dist: html5lib
Requires-Dist: stem
Requires-Dist: psutil
Requires-Dist: pysocks
